llm_testing_suite/__init__.py
llm_testing_suite/code_evaluator.py
llm_testing_suite/llm_testing_suite.py
llm_testlab-0.2.0.dist-info/licenses/LICENSE
llm_testlab-0.2.0.dist-info/METADATA
llm_testlab-0.2.0.dist-info/WHEEL
llm_testlab-0.2.0.dist-info/top_level.txt
llm_testlab-0.2.0.dist-info/RECORD
