Metadata-Version: 2.4
Name: llm-testlab
Version: 0.2.0
Summary: Comprehensive testing suite for LLM evaluation: hallucination detection, consistency, robustness, safety, and multi-language code generation assessment.
Author-email: Sai Vineeth Arumalla <saivineeth147@gmail.com>
License: MIT License
Project-URL: Homepage, https://github.com/Saivineeth147/llm-testlab
Project-URL: Repository, https://github.com/Saivineeth147/llm-testlab
Project-URL: Documentation, https://github.com/Saivineeth147/llm-testlab#readme
Project-URL: Bug Tracker, https://github.com/Saivineeth147/llm-testlab/issues
Keywords: LLM,testing,evaluation,AI,hallucination-detection,code-evaluation,semantic-similarity,NLP,machine-learning
Classifier: Development Status :: 4 - Beta
Classifier: Intended Audience :: Developers
Classifier: Intended Audience :: Science/Research
Classifier: Programming Language :: Python :: 3
Classifier: Programming Language :: Python :: 3.9
Classifier: Programming Language :: Python :: 3.10
Classifier: Programming Language :: Python :: 3.11
Classifier: Programming Language :: Python :: 3.12
Classifier: License :: OSI Approved :: MIT License
Classifier: Operating System :: OS Independent
Classifier: Topic :: Scientific/Engineering :: Artificial Intelligence
Classifier: Topic :: Software Development :: Testing
Classifier: Topic :: Software Development :: Quality Assurance
Requires-Python: >=3.9
License-File: LICENSE
Requires-Dist: numpy==2.3.3
Requires-Dist: sentence-transformers==5.1.1
Requires-Dist: rich
Provides-Extra: faiss
Requires-Dist: faiss-cpu; extra == "faiss"
Provides-Extra: huggingface
Requires-Dist: transformers==4.56.2; extra == "huggingface"
Requires-Dist: huggingface_hub==0.35.0; extra == "huggingface"
Provides-Extra: all
Requires-Dist: faiss-cpu; extra == "all"
Requires-Dist: transformers==4.56.2; extra == "all"
Requires-Dist: huggingface_hub==0.35.0; extra == "all"
Dynamic: license-file
